pyromod/__init__.py
pyromod/filters/__init__.py
pyromod/filters/filters.py
pyromod/helpers/__init__.py
pyromod/helpers/helpers.py
pyromod/listen/__init__.py
pyromod/listen/listen.py
pyromod/nav/__init__.py
pyromod/nav/pagination.py
pyromod/utils/__init__.py
pyromod/utils/utils.py
pyrohappy-1.6.dist-info/COPYING
pyrohappy-1.6.dist-info/COPYING.lesser
pyrohappy-1.6.dist-info/METADATA
pyrohappy-1.6.dist-info/NOTICE
pyrohappy-1.6.dist-info/WHEEL
pyrohappy-1.6.dist-info/top_level.txt
pyrohappy-1.6.dist-info/RECORD
