Metadata-Version: 2.1
Name: pyrohappy
Version: 1.6
Summary: A monkeypatcher add-on for Pyrogram
Home-page: https://github.com/MUTLCC/pyrohappy
Author: MUTLCC
License: LGPLv3+
Platform: UNKNOWN
Classifier: Programming Language :: Python :: 3
Classifier: License :: OSI Approved :: GNU Lesser General Public License v3 or later (LGPLv3+)
Classifier: Operating System :: OS Independent
Requires-Python: >=3.6
License-File: COPYING
License-File: COPYING.lesser
License-File: NOTICE
Requires-Dist: pyrogram
